boringmd/VERSION
boringmd/__init__.py
boringmd/__main__.py
boringmd/front_matter.py
boringmd/invoke.py
boringmd/line_guidance.py
boringmd/normalize.py
boringmd/py.typed
boringmd/transformers/__init__.py
boringmd/transformers/emphasis.py
boringmd/transformers/fenced_code.py
boringmd/transformers/front_matter.py
boringmd/transformers/heading.py
boringmd/transformers/html.py
boringmd/transformers/hyperlink.py
boringmd/transformers/indented_code.py
boringmd/transformers/inline_code.py
boringmd/transformers/line.py
boringmd/transformers/py.typed
boringmd/transformers/strong.py
boringmd/transformers/transformer.py
boringmd/version.py
boringmd-1.2.0.dist-info/LICENSE
boringmd-1.2.0.dist-info/METADATA
boringmd-1.2.0.dist-info/WHEEL
boringmd-1.2.0.dist-info/entry_points.txt
boringmd-1.2.0.dist-info/RECORD
