Metadata-Version: 2.3
Name: boringmd
Version: 1.2.0
Summary: Extract plain text and front matter from Markdown documents
License: MIT
Keywords: markdown,text
Author: Cariad Eccleston
Author-email: cariad@cariad.earth
Requires-Python: ~=3.9
Classifier: Environment :: Console
Classifier: License :: OSI Approved :: MIT License
Classifier: Natural Language :: English
Classifier: Operating System :: OS Independent
Classifier: Programming Language :: Python :: 3
Classifier: Programming Language :: Python :: 3.9
Classifier: Programming Language :: Python :: 3.10
Classifier: Programming Language :: Python :: 3.11
Classifier: Programming Language :: Python :: 3.12
Classifier: Programming Language :: Python :: 3.13
Classifier: Topic :: Text Processing
Classifier: Topic :: Text Processing :: Markup :: Markdown
Classifier: Topic :: Utilities
Classifier: Typing :: Typed
Requires-Dist: lstr (>=1.0,<2.0)
Project-URL: Homepage, https://github.com/cariad/boringmd
